langsmith_evaluation_helper/__init__.py
langsmith_evaluation_helper/builtin_evaluators.py
langsmith_evaluation_helper/cli.py
langsmith_evaluation_helper/load_run_function.py
langsmith_evaluation_helper/loader.py
langsmith_evaluation_helper/schema.py
langsmith_evaluation_helper/utils.py
langsmith_evaluation_helper/llm/__init__.py
langsmith_evaluation_helper/llm/model.py
langsmith_evaluation_helper/llm/prompt_template_wrapper.py
langsmith_evaluation_helper-0.1.5.dist-info/LICENSE
langsmith_evaluation_helper-0.1.5.dist-info/METADATA
langsmith_evaluation_helper-0.1.5.dist-info/WHEEL
langsmith_evaluation_helper-0.1.5.dist-info/entry_points.txt
langsmith_evaluation_helper-0.1.5.dist-info/top_level.txt
langsmith_evaluation_helper-0.1.5.dist-info/RECORD
