Metadata-Version: 2.1
Name: langsmith_evaluation_helper
Version: 0.1.5
Summary: Helper library for langsmith evalution
License: Apache License
Requires-Python: >=3.11
License-File: LICENSE
Requires-Dist: langchain
Requires-Dist: langchain-anthropic
Requires-Dist: langchain-openai
Requires-Dist: langchain-google-genai
Requires-Dist: langchain-google-vertexai
Requires-Dist: langgraph
Requires-Dist: python-dotenv
Requires-Dist: openai
Requires-Dist: pandas
Requires-Dist: uvloop
Requires-Dist: langsmith
Requires-Dist: langchain-community
Provides-Extra: dev
Requires-Dist: pytest ; extra == 'dev'
Requires-Dist: pytest-mock ; extra == 'dev'
Requires-Dist: pytest-env ; extra == 'dev'
Requires-Dist: pytest-dotenv ; extra == 'dev'
Requires-Dist: pytest-asyncio ; extra == 'dev'
Requires-Dist: ruff ; extra == 'dev'
Requires-Dist: mypy ; extra == 'dev'
Requires-Dist: Faker ; extra == 'dev'
Requires-Dist: pyright ; extra == 'dev'
Requires-Dist: types-requests ; extra == 'dev'
Requires-Dist: pytest-cov ; extra == 'dev'
Requires-Dist: types-pyyaml ; extra == 'dev'
Requires-Dist: direnv ; extra == 'dev'
Requires-Dist: build ; extra == 'dev'
Requires-Dist: setuptools ; extra == 'dev'
Requires-Dist: wheel ; extra == 'dev'
Requires-Dist: twine ; extra == 'dev'
Requires-Dist: pip-licenses ; extra == 'dev'
Requires-Dist: reuse ; extra == 'dev'
